gbwhatsapp/__init__.py
gbwhatsapp/__main__.py
gbwhatsapp/replace_package.py
gbwhatsapp/androidx_2_androidy/__init__.py
gbwhatsapp/androidx_2_androidy/convert_androidy.py
gbwhatsapp/gbwhatsapp_2_whatsapp/__init__.py
gbwhatsapp/gbwhatsapp_2_whatsapp/convert_gb.py
gbwhatsapp/gbwhatsapp_2_whatsapp/smali.xml
gbwhatsapp/gbwhatsapp_2_whatsapp/smali_classes2.xml
gbwhatsapp/insertcode/__init__.py
gbwhatsapp/insertcode/getYoSig.py
gbwhatsapp/insertcode/md_and_sec.py
gbwhatsapp/others/__init__.py
gbwhatsapp/others/others.py
gbwhatsapp/public_sort/__init__.py
gbwhatsapp/public_sort/public_sort.py
gbwhatsapp/support_2_supporty/__init__.py
gbwhatsapp/support_2_supporty/convert_supporty.py
gbwhatsapp/yo/dep$1.smali
gbwhatsapp/yo/dep.smali
gbwhatsapp/yo/yo.smali
convertgb-1.0.4.dist-info/LICENSE
convertgb-1.0.4.dist-info/METADATA
convertgb-1.0.4.dist-info/WHEEL
convertgb-1.0.4.dist-info/entry_points.txt
convertgb-1.0.4.dist-info/top_level.txt
convertgb-1.0.4.dist-info/RECORD
